setup.py
sort_me/__init__.py
sort_me/main.py
sort_me/sort.py
sort_me.egg-info/PKG-INFO
sort_me.egg-info/SOURCES.txt
sort_me.egg-info/dependency_links.txt
sort_me.egg-info/not-zip-safe
sort_me.egg-info/top_level.txt