Metadata-Version: 1.0
Name: sort-me
Version: 0.1.4
Summary: Sorting Algorithms
Home-page: UNKNOWN
Author: Yash Arora
Author-email: arorayash905@gmail.com
License: UNKNOWN
Platform: UNKNOWN
